exemplo_slides_adder4bits/adder4bits.vhdl
library ieee;
use ieee.numeric_bit.all;

entity adder4bits is
   port (
      a:         in  bit_vector(3 downto 0);
	   b:         in  bit_vector(3 downto 0);
	   sum:       out bit_vector(3 downto 0);
	   carry_out: out bit
   );
end adder4bits;

architecture adder4bits_arch of adder4bits is
   signal sum_c: bit_vector(4 downto 0);  -- sinal interno que captura o carry
begin
   sum_c <= bit_vector(unsigned('0' & a) + unsigned('0' & b));  -- operandos e resultado com 5 bits (1 a mais que as entradas e saída)
   sum   <= sum_c(3 downto 0);      -- associa a saída 'sum' aos 4 bits menos significativos do sinal interno 'sum_c'
   carry_out <= sum_c(4);           -- associa a saída 'carry_out' ao bit mais significativo do sinal interno 'sum_c'
end adder4bits_arch;

exemplo_slides_adder4bits/adder4bits_tb.vhdl
entity adder4bits_tb is
end entity;

architecture adder4bits_tb_arch of adder4bits_tb is

   -- Declara o componente do DUT
   component adder4bits is
      port (
        	a:         in  bit_vector(3 downto 0);
	    	b:         in  bit_vector(3 downto 0);
	    	sum:       out bit_vector(3 downto 0);
	    	carry_out: out bit
      );
   end component;

   signal a_in, b_in, s_out: bit_vector(3 downto 0);
   signal c_out: bit;

begin
  
   DUT: adder4bits port map (a => a_in, b => b_in, sum => s_out, carry_out => c_out);
   
   gerador_estimulos: process
   begin
      a_in <= "0000";
	  b_in <= "0000";
	  wait for 1 ns;  -- espera estabilizar e verifica a saída
	  assert (c_out & s_out = "00000") report "Fail 0+0" severity error;
	  
	  a_in <= "0001";
	  b_in <= "0001";
	  wait for 1 ns;  -- espera estabilizar e verifica a saída
	  assert (c_out & s_out = "00010") report "Fail 1+1" severity error;

	  a_in <= "1000";
	  b_in <= "1000";
	  wait for 1 ns;  -- espera estabilizar e verifica a saída
	  assert (c_out & s_out = "10000") report "Fail 8+8" severity error;

	  a_in <= "1111";
	  b_in <= "0001";
	  wait for 1 ns;  -- espera estabilizar e verifica a saída
	  assert (c_out & s_out = "10000") report "Fail F+1" severity error;

	  a_in <= "1110";
	  b_in <= "0111";
	  wait for 1 ns;  -- espera estabilizar e verifica a saída
	  assert (c_out & s_out = "10101") report "Fail E+7" severity error;

	  a_in <= "0111";
	  b_in <= "0011";
	  wait for 1 ns;  -- espera estabilizar e verifica a saída
	  assert (c_out & s_out = "01010") report "Fail 7+3" severity error;

	  a_in <= "1100";
	  b_in <= "0101";
	  wait for 1 ns;  -- espera estabilizar e verifica a saída
	  assert (c_out & s_out = "10001") report "Fail C+5" severity error;

	  -- Limpa entradas (opcional)
	  a_in <= "0000";
	  b_in <= "0000";
	  
	  -- Informa fim do teste
	  assert false report "Test done." severity note;	  
	  wait;  -- pára a execução do simulador, caso contrário este process é reexecutado indefinidamente.
   end process;
   

end adder4bits_tb_arch;

exemplo_slides_adder4bits/simul.vcd
$date
  Mon Sep  7 19:07:08 2020
$end
$version
  GHDL v0
$end
$timescale
  1 fs
$end
$scope module standard $end
$upscope $end
$scope module numeric_bit $end
$upscope $end
$scope module adder4bits_tb $end
$var reg 4 ! a_in[3:0] $end
$var reg 4 " b_in[3:0] $end
$var reg 4 # s_out[3:0] $end
$var reg 1 $ c_out $end
$scope module dut $end
$var reg 4 % a[3:0] $end
$var reg 4 & b[3:0] $end
$var reg 4 ' sum[3:0] $end
$var reg 1 ( carry_out $end
$var reg 5 ) sum_c[4:0] $end
$upscope $end
$upscope $end
$enddefinitions $end
#0
b0000 !
b0000 "
b0000 #
0$
b0000 %
b0000 &
b0000 '
0(
b00000 )
#1000000
b0001 !
b0001 "
b0010 #
b0001 %
b0001 &
b0010 '
b00010 )
#2000000
b1000 !
b1000 "
b0000 #
1$
b1000 %
b1000 &
b0000 '
1(
b10000 )
#3000000
b1111 !
b0001 "
b1111 %
b0001 &
#4000000
b1110 !
b0111 "
b0101 #
b1110 %
b0111 &
b0101 '
b10101 )
#5000000
b0111 !
b0011 "
b1010 #
0$
b0111 %
b0011 &
b1010 '
0(
b01010 )
#6000000
b1100 !
b0101 "
b0001 #
1$
b1100 %
b0101 &
b0001 '
1(
b10001 )
#7000000
b0000 !
b0000 "
b0000 #
0$
b0000 %
b0000 &
b0000 '
0(
b00000 )
